hdxrate/__init__.py
hdxrate/constants.txt
hdxrate/hdxrate.py
hdxrate-0.2.3.dist-info/licenses/AUTHORS
hdxrate-0.2.3.dist-info/licenses/AUTHORS.rst
hdxrate-0.2.3.dist-info/licenses/LICENSE
hdxrate-0.2.3.dist-info/METADATA
hdxrate-0.2.3.dist-info/WHEEL
hdxrate-0.2.3.dist-info/pbr.json
hdxrate-0.2.3.dist-info/top_level.txt
hdxrate-0.2.3.dist-info/RECORD
