Metadata-Version: 2.4
Name: HDXrate
Version: 0.2.3
Summary: Calculate HDX intrinsic exchange rates.
Home-page: https://github.com/Jhsmit/HDXrate
Author: Jochem Smit
Author-email: jhmit@gmail.com
License: GNU GPL
Keywords: HDX-MS,exchange rate
Classifier: Development Status :: 3 - Alpha
Classifier: Intended Audience :: Science/Research
Classifier: License :: OSI Approved :: GNU General Public License v3 or later (GPLv3+)
Classifier: Topic :: Scientific/Engineering :: Bio-Informatics
Classifier: Programming Language :: Python :: 3.6
Classifier: Programming Language :: Python :: 3.7
Classifier: Programming Language :: Python :: 3.8
Classifier: Programming Language :: Python :: 3.9
Requires-Python: >=3.6
License-File: LICENSE
License-File: AUTHORS
License-File: AUTHORS.rst
Requires-Dist: numpy
Dynamic: author
Dynamic: author-email
Dynamic: classifier
Dynamic: description
Dynamic: home-page
Dynamic: keywords
Dynamic: license
Dynamic: license-file
Dynamic: requires-dist
Dynamic: requires-python
Dynamic: summary
